robotape/__init__.py
robotape/agents/__init__.py
robotape/agents/base.py
robotape/agents/llm.py
robotape/agents/mcpllm.py
robotape/agents/simple.py
robotape/llm/__init__.py
robotape/llm/base.py
robotape/llm/providers/__init__.py
robotape/llm/providers/anthropic.py
robotape/llm/providers/huggingface.py
robotape/llm/providers/openai.py
robotape/mcp/__init__.py
robotape/mcp/client.py
robotape/mcp/mcp.py
robotape/mcp/server.py
robotape/mcp/tools.py
robotape/models/__init__.py
robotape/models/base.py
robotape/models/steps.py
robotape/storage.py
robotape/tape.py
robotape/tools.py
robotape/utils/__init__.py
robotape/utils/logging.py
robotape/utils/validation.py
robotape-0.6.0.dist-info/LICENSE
robotape-0.6.0.dist-info/METADATA
robotape-0.6.0.dist-info/WHEEL
robotape-0.6.0.dist-info/RECORD
