Metadata-Version: 2.1
Name: robotape
Version: 0.6.0
Summary: A lightweight agent framework
Home-page: https://github.com/andrewlwn77/robotape
License: MIT
Keywords: agent,framework,autonomous,AI
Author: Andrew Lewin
Requires-Python: >=3.9
Classifier: License :: OSI Approved :: MIT License
Classifier: Programming Language :: Python :: 3
Classifier: Programming Language :: Python :: 3.9
Classifier: Programming Language :: Python :: 3.10
Classifier: Programming Language :: Python :: 3.11
Classifier: Programming Language :: Python :: 3.12
Classifier: Programming Language :: Python :: 3.13
Requires-Dist: aiohttp (>=3.8.0)
Requires-Dist: anthropic (>=0.42.0)
Requires-Dist: asyncio (>=3.4.3)
Requires-Dist: huggingface-hub (>=0.27.0)
Requires-Dist: mcp (>=1.2.0)
Requires-Dist: mirascope[anthropic,mcp] (>=1.14.0)
Requires-Dist: openai (>=1.59.3)
Requires-Dist: pydantic (>=2.0.0)
Requires-Dist: python-dotenv (>=1.0.0)
Requires-Dist: sqlalchemy (>=2.0.0)
Requires-Dist: sqlmodel (>=0.0.8)
Requires-Dist: typing-extensions (>=4.5.0)
Requires-Dist: uuid (>=1.30)
Project-URL: Documentation, https://github.com/andrewlwn77/robotape/tree/main/docs
Project-URL: Repository, https://github.com/andrewlwn77/robotape
